pyss/_arguments.py
pyss/_constants.py
pyss/_environment.py
pyss/_execution.py
pyss/_logging.py
pyss/_scripts.py
pyss/_types.py
pyss/_validator.py
pyss/main.py
pyss-1.1.7.dist-info/LICENSE
pyss-1.1.7.dist-info/METADATA
pyss-1.1.7.dist-info/WHEEL
pyss-1.1.7.dist-info/entry_points.txt
pyss-1.1.7.dist-info/top_level.txt
pyss-1.1.7.dist-info/RECORD
