Metadata-Version: 2.1
Name: pyss
Version: 1.1.7
Summary: Adds a utility for running pyss.yaml files.
Author-email: Nathan Fiscaletti <nate.fiscaletti@gmail.com>
Project-URL: Homepage, https://github.com/nathan-fiscaletti/pyss
Classifier: Programming Language :: Python :: 3
Classifier: License :: OSI Approved :: MIT License
Classifier: Operating System :: OS Independent
Requires-Python: >=3.7
License-File: LICENSE
Requires-Dist: pyyaml>=6.0
Requires-Dist: termcolor>=2.2.0
Requires-Dist: importlib-metadata>=5.0.0
Requires-Dist: packaging>=21.3
Requires-Dist: jsonschema>=4.20.0
